pykatana/__init__.py
pykatana/__main__.py
pykatana/__program.py
pykatana/__data/logo/facebook_cover_photo_1.png
pykatana/__data/logo/facebook_cover_photo_2.png
pykatana/__data/logo/facebook_profile_image.png
pykatana/__data/logo/favicon.png
pykatana/__data/logo/icon.ico
pykatana/__data/logo/instagram_profile_image.png
pykatana/__data/logo/linkedin_banner_image_1.png
pykatana/__data/logo/linkedin_banner_image_2.png
pykatana/__data/logo/linkedin_profile_image.png
pykatana/__data/logo/logo.png
pykatana/__data/logo/logo_transparent.png
pykatana/__data/logo/pinterest_board_photo.png
pykatana/__data/logo/pinterest_profile_image.png
pykatana/__data/logo/twitter_header_photo_1.png
pykatana/__data/logo/twitter_header_photo_2.png
pykatana/__data/logo/twitter_profile_image.png
pykatana/__data/logo/youtube_profile_image.png
pykatana/__make/clean.sh
pykatana/__make/make.bat
pykatana/__make/make.sh
pykatana/__make/pykatana.py
pykatana/__pykatana_init/gitignore
pykatana/__pykatana_init/src/make.py
pykatana/__pykatana_init/src/pykatana/engine/__engine.py
pykatana/__pykatana_init/src/pykatana/engine/__init__.py
pykatana/__pykatana_init/src/static/migration/migration.css
pykatana/__pykatana_init/src/static/migration/migration.css.map
pykatana/__pykatana_init/src/static/migration/migration.scss
pykatana/__pykatana_init/src/templates/index.html
pykatana/engine/__DirWatcher.py
pykatana/engine/__EZJinja.py
pykatana/engine/__Jinjutsu.py
pykatana/engine/__dict.py
pykatana/engine/__init__.py
pykatana/engine/__server.py
pykatana-1.0.12.dist-info/METADATA
pykatana-1.0.12.dist-info/WHEEL
pykatana-1.0.12.dist-info/entry_points.txt
pykatana-1.0.12.dist-info/top_level.txt
pykatana-1.0.12.dist-info/RECORD
