Metadata-Version: 2.1
Name: pykatana
Version: 1.0.12
Summary: A Python-based build system for creating static websites with ease and flexibility.
Home-page: https://github.com/adanayi/pykatana
Author: Abolfazl Danayi
Author-email: adanayidet@gmail.com
License: UNKNOWN
Platform: UNKNOWN
Classifier: Development Status :: 3 - Alpha
Classifier: Programming Language :: Python :: 3
Classifier: License :: OSI Approved :: GNU General Public License v3 (GPLv3)
Classifier: Operating System :: OS Independent
Requires-Dist: jinja2
Requires-Dist: watchdog
